Core/SimpleImageIOCore.dll
Core/SimpleImageIOCore.lib
PyWrapper/simpleimageio/__init__.py
PyWrapper/simpleimageio/image.py
simpleimageio/SimpleImageIOCore.dll
simpleimageio/SimpleImageIOCore.lib
simpleimageio/__init__.py
simpleimageio/image.py
SimpleImageIO-0.2.3.dist-info/LICENSE
SimpleImageIO-0.2.3.dist-info/METADATA
SimpleImageIO-0.2.3.dist-info/WHEEL
SimpleImageIO-0.2.3.dist-info/top_level.txt
SimpleImageIO-0.2.3.dist-info/RECORD
