Metadata-Version: 2.1
Name: SimpleImageIO
Version: 0.2.3
Summary: Python wrapper around TinyEXR and stb_image
Home-page: https://github.com/pgrit/SimpleImageIO
Author: Pascal Grittmann
License: UNKNOWN
Platform: UNKNOWN
Classifier: Programming Language :: Python :: 3
Classifier: License :: OSI Approved :: MIT License
Classifier: Operating System :: OS Independent
Requires-Python: >=3.6
Requires-Dist: numpy
